pycrawl/__init__.py
pycrawl/carray.py
pycrawl/pycrawl.py
pycrawl-3.1.0.dist-info/LICENSE
pycrawl-3.1.0.dist-info/METADATA
pycrawl-3.1.0.dist-info/WHEEL
pycrawl-3.1.0.dist-info/top_level.txt
pycrawl-3.1.0.dist-info/RECORD
